{
  "main": {
    "id": "5adc9789b149c12b",
    "type": "split",
    "children": [
      {
        "id": "8e8b8dc850191b8e",
        "type": "tabs",
        "children": [
          {
            "id": "f6c3004edf46a52c",
            "type": "leaf",
            "state": {
              "type": "markdown",
              "state": {
                "file": "Método iterativo de Gauss-Jacobi.md",
                "mode": "source",
                "source": false
              }
            }
          }
        ]
      }
    ],
    "direction": "vertical"
  },
  "left": {
    "id": "aba031cf518c68bc",
    "type": "split",
    "children": [
      {
        "id": "cff99ca1fb221cce",
        "type": "tabs",
        "children": [
          {
            "id": "d8409a2bfb18d08d",
            "type": "leaf",
            "state": {
              "type": "file-explorer",
              "state": {
                "sortOrder": "alphabetical"
              }
            }
          },
          {
            "id": "f5d5e416984a4132",
            "type": "leaf",
            "state": {
              "type": "search",
              "state": {
                "query": "",
                "matchingCase": false,
                "explainSearch": false,
                "collapseAll": false,
                "extraContext": false,
                "sortOrder": "alphabetical"
              }
            }
          },
          {
            "id": "a4266d2837ecd846",
            "type": "leaf",
            "state": {
              "type": "bookmarks",
              "state": {}
            }
          }
        ]
      }
    ],
    "direction": "horizontal",
    "width": 318.5
  },
  "right": {
    "id": "120a8d0aca4989ea",
    "type": "split",
    "children": [
      {
        "id": "5ba50c275586ae3c",
        "type": "tabs",
        "children": [
          {
            "id": "ff2695a686dfa7d5",
            "type": "leaf",
            "state": {
              "type": "backlink",
              "state": {
                "file": "Método iterativo de Gauss-Jacobi.md",
                "collapseAll": false,
                "extraContext": false,
                "sortOrder": "alphabetical",
                "showSearch": false,
                "searchQuery": "",
                "backlinkCollapsed": false,
                "unlinkedCollapsed": true
              }
            }
          },
          {
            "id": "27d8d6470a86215b",
            "type": "leaf",
            "state": {
              "type": "outgoing-link",
              "state": {
                "file": "Método iterativo de Gauss-Jacobi.md",
                "linksCollapsed": false,
                "unlinkedCollapsed": true
              }
            }
          },
          {
            "id": "d09693b02de674a8",
            "type": "leaf",
            "state": {
              "type": "tag",
              "state": {
                "sortOrder": "frequency",
                "useHierarchy": true
              }
            }
          },
          {
            "id": "191f50fd4d288d2b",
            "type": "leaf",
            "state": {
              "type": "outline",
              "state": {
                "file": "Método iterativo de Gauss-Jacobi.md"
              }
            }
          }
        ]
      }
    ],
    "direction": "horizontal",
    "width": 300,
    "collapsed": true
  },
  "left-ribbon": {
    "hiddenItems": {
      "switcher:Open quick switcher": false,
      "graph:Open graph view": false,
      "canvas:Create new canvas": false,
      "daily-notes:Open today's daily note": false,
      "templates:Insert template": false,
      "command-palette:Open command palette": false,
      "obsidian-excalidraw-plugin:Create new drawing": false,
      "table-editor-obsidian:Advanced Tables Toolbar": false,
      "vscode-editor:Create Code File": false
    }
  },
  "active": "f6c3004edf46a52c",
  "lastOpenFiles": [
    "Ajuste de Curvas.md",
    "images/FATLU-3.png",
    "images/FATLU-4.png",
    "images/iterativas-3.png",
    "Sistemas de equações lineares.md",
    "Métodos iterativos para Sistema Lineares.md",
    "images/Pasted image 20240709224613.png",
    "images/20240701_145904.jpg",
    "images/20240703_163649.jpg",
    "Integração Numérica.md",
    "images/Pasted image 20240709225331.png",
    "images/20240703_162216.jpg",
    "images/20240703_161028.jpg",
    "images/20240703_155301.jpg",
    "Interpolação Polinomial.md",
    "Equações diferenciais.md",
    "Estudo sobre erros.md",
    "Fatoração LU.md",
    "Math Simbols.md",
    "Método de eliminação de Gauss.md",
    "Método iterativo de Gauss-Jacobi.md",
    "Zeros de funcoes/Metodo das Secantes.md",
    "Excalidraw/Método de Newton-Raphson (das Tangentes) 2024-04-08 14.40.19.excalidraw.md",
    "Zeros de funcoes/Método de Newton-Raphson (das Tangentes).md",
    "Zeros de funcoes/Teorema de Bolzano.md",
    "Zeros de funcoes/Zeros de funções.md",
    "Excalidraw/MetodoFalsaPosicao2024-04-03-15.53.53.excalidraw.md",
    "Zeros de funcoes/Método da Falsa posição.md",
    "Zeros de funcoes/Método Gráfico.md",
    "images",
    "Zeros de funcoes/Método da Bisseção.md",
    "Excalidraw",
    "__init__.py",
    "Zeros de funcoes/__init__.py",
    "Zeros de funcoes"
  ]
}